{
  "id": "model_stave",
  "version": 2,
  "nodes": [
    { "x": 0, "y": 0, "z": 0, "materialId": 100 },
    { "x": 0, "y": 1, "z": 0, "materialId": 100 },
    { "x": 0, "y": 2, "z": 0, "materialId": 100 },
    { "x": 0, "y": 3, "z": 0, "materialId": 100 },
    { "x": 0, "y": 4, "z": 0, "materialId": 100 },
    { "x": 0, "y": 5, "z": 0, "materialId": 100 },
    { "x": 0, "y": 6, "z": 0, "materialId": 100 },
    { "x": 0, "y": 7, "z": 0, "materialId": 100 },
    { "x": 0, "y": 0, "z": 1, "materialId": 100 },
    { "x": 0, "y": 7, "z": 1, "materialId": 100 }
  ],
  "subObjects": [],
  "materials": [100]
}
